<?xml version='1.0' encoding='utf-8'?><m:page id='381e6053-aa55-4b15-9cf1-0956d6727a78' xmlns='http://www.w3.org/1999/xhtml' title='Department Overview' class='layout-atlas layout-atlas-responsive-topbar' xmlns:m='http://schemas.mendix.com/forms/1.0'><m:layouts><m:layout path='Atlas_UI_Resources/Atlas_TopBar.layout.xml'></m:layout></m:layouts><m:arguments><m:argument parameterName='2d529b25-2e79-4402-a37b-46467a6bc14f'><div data-mendix-id='3_0' class='mx-layoutgrid mx-layoutgrid-fluid container-fluid mx-name-layoutGrid1'><div class='row'><div class='col-lg col-md col'><div data-mendix-id='3_1' data-mendix-type='mxui.widget.ReactWidgetWrapper' data-mendix-props='"widgetTree":[{"widget":"Text","widgetId":"3_1","props":{"name":"text1","caption":{"$type":"DynamicTextProperty","template":{"elements":["Department"],"friendlyId":"MyFirstModule.Department_Overview.text1"}},"renderMode":"h2","class":"mx-name-text1"}}]'></div><div data-mendix-id='3_6' data-mendix-type='mxui.widget.DataGrid' data-mendix-props='"friendlyId":"MyFirstModule.Department_Overview.grid1","entity":"MyFirstModule.Department","schema":"4726f7a0-1dba-4450-86f2-bbeabc113974","config":{"locale":"en_US","gridType":"Standalone","gridpresentation":{"rows":20,"columns":1,"controlbar":true,"pagingbar":true,"searchbar":true,"waitforsearch":false,"selectionmode":"single","editable":false,"sortable":true,"refresh":0,"selectfirst":false,"showemptyrows":false},"datasource":{"friendlyId":"MyFirstModule.Department_Overview.grid1","type":"database","path":"MyFirstModule.Department","offlineConstraints":[],"xpathConstraints":""},"searchOptions":{"searchBar":true,"toggleable":true,"toggledByDefault":true},"searchElements":[{"searchInputName":"searchField1","defaults":null,"defaultsParser":"Simple","caption":"Name","path":"Name","operator":"contains"}],"controlBar":{"gridTools":[{"mxid":"3_2","friendlyId":"MyFirstModule.Department_Overview.searchButton1","name":"searchButton1","caption":{"elements":["Search"],"friendlyId":"MyFirstModule.Department_Overview.searchButton1"},"title":"","cssClass":"btn-default"},{"mxid":"3_3","friendlyId":"MyFirstModule.Department_Overview.newButton1","name":"newButton1","caption":{"elements":["New"],"friendlyId":"MyFirstModule.Department_Overview.newButton1"},"title":"","cssClass":"btn-default","visibleForRoles":["Administrator"]},{"mxid":"3_4","friendlyId":"MyFirstModule.Department_Overview.actionButton2","name":"actionButton2","caption":{"elements":["Edit"],"friendlyId":"MyFirstModule.Department_Overview.actionButton2"},"title":"","cssClass":"btn-default","visibleForRoles":["Administrator"]},{"mxid":"3_5","friendlyId":"MyFirstModule.Department_Overview.actionButton1","name":"actionButton1","caption":{"elements":["Delete"],"friendlyId":"MyFirstModule.Department_Overview.actionButton1"},"title":"","cssClass":"btn-default","visibleForRoles":["Administrator","Manager"]}],"gridActions":[{"keyValue":"3_2","gridFunction":"ToggleSearch"},{"keyValue":"3_3","gridFunction":"InvokeAction","params":{"action":{"type":"createObject","argMap":{},"config":{"entity":"MyFirstModule.Department","pageSettings":{"name":"MyFirstModule/Department_NewEdit.page.xml","location":"modal","resizable":true,"allowedRoles":["Administrator"]},"allowedRoles":["Administrator"]}}}},{"keyValue":"3_4","gridFunction":"InvokeAction","params":{"action":{"type":"openPage","argMap":{"$pageParameter":{"widget":"3_6","source":"selection"}},"config":{"name":"MyFirstModule/Department_NewEdit.page.xml","location":"modal","resizable":true,"allowedRoles":["Administrator"]}},"maintainSelection":true}},{"keyValue":"3_5","gridFunction":"InvokeAction","params":{"action":{"type":"deleteObject","argMap":{"$object":{"widget":"3_6","source":"selection"}},"config":{"closePage":false}},"maintainSelection":false}}]},"defaultButton":{"clickType":"double","mxid":"3_4"},"griddata":[{"tag":"Name","name":"column1","editable":false,"render":"String","display":{"width":"100%","string":"Name"}}],"plugins":{}},"caption":{"elements":[],"friendlyId":"MyFirstModule.Department_Overview.grid1"}' class='mx-datagrid mx-name-grid1' tabindex='0'></div></div></div></div></m:argument></m:arguments></m:page>